MANIFEST.in
README.md
setup.cfg
setup.py
equity_db/__init__.py
equity_db.egg-info/PKG-INFO
equity_db.egg-info/SOURCES.txt
equity_db.egg-info/dependency_links.txt
equity_db.egg-info/requires.txt
equity_db.egg-info/top_level.txt
equity_db/api/__init__.py
equity_db/api/mongo_connection.py
equity_db/api/mongo_status.py
equity_db/query/__init__.py
equity_db/query/asset_query.py
equity_db/query/db_query.py
equity_db/query/joined_asset_query.py
equity_db/variables/__init__.py
equity_db/variables/base_variables.py
equity_db/variables/compusat_variables.py
equity_db/variables/crsp_variables.py
equity_db/variables/dispatcher.py
equity_db/variables/metadata/compustat.csv
equity_db/variables/metadata/crsp.csv
equity_db/write/__init__.py
equity_db/write/insert_to_db.py
equity_db/write/prep_for_insert.py