Metadata-Version: 1.1
Name: equity-db
Version: 1.2
Summary: Python package which manages CRSP & Compustat data. Uses MongoDB to store and query data.
Home-page: https://github.com/Alexd14/equity-db
Author: Alex DiCarlo
Author-email: dicarlo.a@northeastern.edu
License: MIT
Download-URL: https://github.com/Alexd14/equity-db/archive/refs/tags/v1.1.tar.gz
Keywords: CRSP,Compustat,stock database
Platform: UNKNOWN
Classifier: Development Status :: 3 - Alpha
Classifier: Intended Audience :: Developers
Classifier: Topic :: Software Development :: Build Tools
Classifier: License :: OSI Approved :: MIT License
Classifier: Programming Language :: Python :: 3.6
Classifier: Programming Language :: Python :: 3.7
Classifier: Programming Language :: Python :: 3.8
Classifier: Programming Language :: Python :: 3.9
